kidx_core_sdk/__init__.py
kidx_core_sdk/constants.py
kidx_core_sdk/endpoint.py
kidx_core_sdk/events.py
kidx_core_sdk/executor.py
kidx_core_sdk/forms.py
kidx_core_sdk/utils.py
kidx_core_sdk/version.py
kidx_core_sdk/cli/__init__.py
kidx_core_sdk/cli/arguments.py
kidx_core_sdk-0.0.1a2.dist-info/LICENSE.txt
kidx_core_sdk-0.0.1a2.dist-info/METADATA
kidx_core_sdk-0.0.1a2.dist-info/WHEEL
kidx_core_sdk-0.0.1a2.dist-info/top_level.txt
kidx_core_sdk-0.0.1a2.dist-info/RECORD
