Metadata-Version: 2.1
Name: kidx-core-sdk
Version: 0.0.1a2
Summary: Machine learning based dialogue engine for conversational software.
Home-page: https://rasa.com
Author: Kidx AI Technologies Education
Author-email: nlp@mykidx.com
Maintainer: Kidx NLP
Maintainer-email: nlp@mykidx.com
License: Apache 2.0
Download-URL: http://git.mykidx.com/nlp/kidx_core_sdk/-/archive/0.0.1a2/kidx_core_sdk-0.0.1a2.tar.gz
Project-URL: Bug Reports, http://git.mykidx.com/nlp/kidx-nlu/issues
Project-URL: Documentation, https://docs.rasa.com/core
Project-URL: Source, http://git.mykidx.com/nlp/kidx_core_sdk
Keywords: nlp machine-learning machine-learning-library bot bots botkit kidx conversational-agents conversational-ai chatbotchatbot-framework bot-framework
Platform: UNKNOWN
Classifier: Development Status :: 4 - Beta
Classifier: Intended Audience :: Developers
Classifier: License :: OSI Approved :: Apache Software License
Classifier: Programming Language :: Python
Classifier: Programming Language :: Python :: 2.7
Classifier: Programming Language :: Python :: 3.5
Classifier: Programming Language :: Python :: 3.6
Classifier: Topic :: Software Development :: Libraries
Requires-Dist: future (~=0.16)
Requires-Dist: typing (~=3.0)
Requires-Dist: requests (~=2.20)
Requires-Dist: ConfigArgParse (~=0.13.0)
Requires-Dist: coloredlogs (~=10.0)
Requires-Dist: flask (~=1.0)
Requires-Dist: flask-cors (~=3.0)
Requires-Dist: gevent (~=1.2)
Requires-Dist: six (~=1.11)
Provides-Extra: test
Requires-Dist: pytest (~=3.0); extra == 'test'
Requires-Dist: pytest-pep8 (~=1.0); extra == 'test'
Requires-Dist: pytest-cov (~=2.0); extra == 'test'
